turbodict/__init__.py
turbodict/_attrdict.cpython-39-x86_64-linux-gnu.so
turbodict-0.1.0.dist-info/WHEEL
turbodict-0.1.0.dist-info/METADATA
turbodict-0.1.0.dist-info/RECORD
turbodict-0.1.0.dist-info/top_level.txt
turbodict-0.1.0.dist-info/LICENSE
